islandest/__init__.py
islandest/execute.py
islandest/finalize.py
islandest/help.py
islandest/main.py
islandest/misc.py
islandest/parse.py
islandest/run.py
islandest/bin/aragorn
islandest/bin/bedtools
islandest/bin/blastn
islandest/bin/bruce
islandest/bin/hmmsearch
islandest/bin/makeblastdb
islandest/bin/prodigal
islandest/data/Phage_integrase.hmm
islandest-0.0.0.dev4.dist-info/METADATA
islandest-0.0.0.dev4.dist-info/WHEEL
islandest-0.0.0.dev4.dist-info/entry_points.txt
islandest-0.0.0.dev4.dist-info/top_level.txt
islandest-0.0.0.dev4.dist-info/RECORD
